Workbook

Sheet Inputs
A1: CAC / LTV MODEL — INPUTS
A2: Blue cells are inputs. Black cells are formulas. Update inputs only.
A4: REVENUE INPUTS
A5: Metric | B5: Value | C5: Notes
A6: Monthly ARPU (Average Revenue Per User) | B6: 500 | C6: Average monthly revenue per paying customer
A7: Annual Contract Value (ACV) | B7: 6000 | C7: ARPU x 12 (auto-calculated on Unit Econ sheet)
A8: Gross Margin % | B8: 0.72 | C8: Revenue minus COGS; SaaS benchmark: 70-85%
A9: Monthly Net Revenue Retention (NRR) | B9: 1.03 | C9: Include expansion; >100% = negative churn
A10: Monthly Churn Rate | B10: 0.02 | C10: % of customers lost per month; 2% ≈ 22% annual
A11: Monthly Expansion Rate | B11: 0.005 | C11: Upsell/cross-sell MRR growth per month
A13: ACQUISITION INPUTS
A14: Metric | B14: Value | C14: Notes
A15: Sales & Marketing Spend (period, $) | B15: 250000 | C15: Total S&M spend: salaries, tools, ads, events
A16: New Customers Acquired (period) | B16: 100 | C16: New logos closed in same period as spend
A17: Onboarding Cost per Customer ($) | B17: 200 | C17: Implementation, CS setup, training costs
A18: Sales Headcount | B18: 8 | C18: AEs + SDRs included in S&M spend above
A19: Marketing Headcount | B19: 4 | C19: Marketing FTEs included in S&M spend above
A20: DISCOUNT & MODEL SETTINGS
A21: Metric | B21: Value | C21: Notes
A22: Annual Discount Rate (WACC / Hurdle) | B22: 0.1 | C22: Used for NPV-adjusted LTV; typical SaaS: 8-15%
A23: Cohort Simulation Periods (months) | B23: 36 | C23: Months to project cohort revenue and retention
A24: Cohort Size (customers) | B24: 100 | C24: Starting customers for cohort model

Sheet Unit Economics
A1: UNIT ECONOMICS SUMMARY
A3: KEY INPUTS (from Inputs sheet)
A4: Metric | B4: Value | C4: Benchmark
A5: Monthly ARPU | B5: =Inputs!B6 -> 500 | C5: N/A
A6: Gross Margin % | B6: =Inputs!B8 -> 0.72 | C6: 70-85% (SaaS)
A7: Monthly Churn Rate | B7: =Inputs!B10 -> 0.02 | C7: < 2%
A8: Monthly Expansion Rate | B8: =Inputs!B11 -> 0.005 | C8: > 0.5%
A9: S&M Spend | B9: =Inputs!B15 -> 250000 | C9: N/A
A10: New Customers | B10: =Inputs!B16 -> 100 | C10: N/A
A11: Onboarding Cost/Cust. | B11: =Inputs!B17 -> 200 | C11: < $500
A14: CUSTOMER ACQUISITION COST (CAC)
A15: Metric | B15: Value | C15: Notes
A16: Blended CAC | B16: =Inputs!B15/Inputs!B16+Inputs!B17 -> 2700 | C16: Total S&M / New Customers + Onboarding
A17: Sales-Only CAC | B17: =Inputs!B15/Inputs!B16 -> 2500 | C17: S&M spend ÷ new customers
A18: Cost per Lead (est.) | B18: =Inputs!B15/(Inputs!B16*10) -> 250 | C18: Assumes 10% lead-to-close rate
A20: LIFETIME VALUE (LTV)
A21: Metric | B21: Value | C21: Notes
A22: Monthly Gross Profit / Customer | B22: =Inputs!B6*Inputs!B8 -> 360 | C22: ARPU × Gross Margin
A23: Net Monthly Churn | B23: =MAX(Inputs!B10-Inputs!B11,0.001) -> 0.015 | C23: Churn minus expansion (floor 0.1%)
A24: LTV — Simple | B24: =IF(B22<=0,"∞",ROUND(Inputs!B6*Inputs!B8/B22,2)) -> 1 | C24: ARPU × GM% / Net Churn
A25: ACV (Annual Contract Value) | B25: =Inputs!B6*12 -> 6000 | C25: ARPU × 12
A26: Average Customer Lifespan (mo.) | B26: =IF(B22<=0,999,ROUND(1/B22,1)) -> 0 | C26: 1 / Net Churn Rate
A28: HEALTH RATIOS
A29: Metric | B29: Value | C29: Target / Benchmark
A30: LTV:CAC Ratio | B30: =IFERROR(B24/B16,"N/A") -> 0.00037037037 | C30: > 3.0x (benchmark)
A31: CAC Payback Period (mo.) | B31: =IFERROR(B16/B22,"N/A") -> 7.5 | C31: < 12 months
A32: Magic Number | B32: =IF(Inputs!B15>0,(Inputs!B16*Inputs!B6*12)/Inputs!B15,"N/A") -> 2.4 | C32: > 0.75 (efficient growth)
A33: Annual Churn Rate | B33: =1-(1-Inputs!B10)^12 -> 0.21528328 | C33: < 15% (B2B SaaS)
A34: Annual NRR | B34: =(1+Inputs!B11-Inputs!B10)^12 -> 0.83413197 | C34: > 100% (expansion > churn)

Sheet Scenarios
A1: SCENARIO ANALYSIS — BEST / BASE / WORST
A3: Metric | B3: Bear Case | C3: Base Case | D3: Bull Case
A4: Monthly ARPU ($) | B4: 300 | C4: 500 | D4: 800
A5: Gross Margin % | B5: 0.6 | C5: 0.72 | D5: 0.82
A6: Monthly Churn Rate | B6: 0.04 | C6: 0.02 | D6: 0.01
A7: Monthly Expansion Rate | B7: 0 | C7: 0.005 | D7: 0.015
A8: S&M Spend ($) | B8: 300000 | C8: 250000 | D8: 200000
A9: New Customers | B9: 60 | C9: 100 | D9: 150
A10: Onboarding Cost/Cust. ($) | B10: 400 | C10: 200 | D10: 100
A13: COMPUTED OUTPUTS
A14: Metric | B14: Bear Case | C14: Base Case | D14: Bull Case
A15: Blended CAC ($) | B15: =B8/B9+B10 -> 5400 | C15: =C8/C9+C10 -> 2700 | D15: =D8/D9+D10 -> 1433.3333
A16: LTV — Simple ($) | B16: =IF((B6-B7)<=0,"∞",ROUND(B4*B5/(B6-B7),2)) -> 4500 | C16: =IF((C6-C7)<=0,"∞",ROUND(C4*C5/(C6-C7),2)) -> 24000 | D16: =IF((D6-D7)<=0,"∞",ROUND(D4*D5/(D6-D7),2)) -> ∞
A17: LTV:CAC Ratio | B17: =IFERROR((B4*B5/MAX(B6-B7,0.001))/(B8/B9+B10),"N/A") -> 0.83333333 | C17: =IFERROR((C4*C5/MAX(C6-C7,0.001))/(C8/C9+C10),"N/A") -> 8.8888889 | D17: =IFERROR((D4*D5/MAX(D6-D7,0.001))/(D8/D9+D10),"N/A") -> 457.67442
A18: Payback Period (months) | B18: =IFERROR((B8/B9+B10)/(B4*B5),"N/A") -> 30 | C18: =IFERROR((C8/C9+C10)/(C4*C5),"N/A") -> 7.5 | D18: =IFERROR((D8/D9+D10)/(D4*D5),"N/A") -> 2.1849593
A19: Magic Number | B19: =IFERROR((B9*B4*12)/B8,"N/A") -> 0.72 | C19: =IFERROR((C9*C4*12)/C8,"N/A") -> 2.4 | D19: =IFERROR((D9*D4*12)/D8,"N/A") -> 7.2
A20: Annual Churn Rate | B20: =1-(1-B6)^12 -> 0.38729024 | C20: =1-(1-C6)^12 -> 0.21528328 | D20: =1-(1-D6)^12 -> 0.11361513

Sheet Dashboard
A1: UNIT ECONOMICS DASHBOARD
A2: Live-linked from Inputs and Unit Economics sheets
A4: BLENDED CAC | D4: LTV (SIMPLE)
A5: ='Unit Economics'!B16 -> 2700 | D5: ='Unit Economics'!B24 -> 1
A8: LTV:CAC RATIO | D8: CAC PAYBACK (MONTHS)
A9: ='Unit Economics'!B30 -> 0.00037037037 | D9: ='Unit Economics'!B31 -> 7.5
A12: MAGIC NUMBER | D12: ANNUAL NRR
A13: ='Unit Economics'!B32 -> 2.4 | D13: ='Unit Economics'!B34 -> 0.83413197
